[{"Bottom_Left":[47.0,0],"Top_Left":[40.6830601093,68],"Top_Right":[123.2303030303,68],"Bottom_Right":[77.0727272727,0],"Player_1":[53.0,6.0],"Player_1_video":[234.5,464.0],"Player_2":[75.0,4.0],"Player_2_video":[869.5,417.0],"Player_3":[58.0,11.0],"Player_3_video":[350.5,396.0],"Player_4":[49.0,15.0],"Player_4_video":[104.5,379.0],"Player_6":[65.0,4.0],"Player_6_video":[607.0,444.0],"Player_7":[58.0,0.0],"Player_7_video":[411.0,526.0],"Player_10":[79.0,6.0],"Player_10_video":[962.5,384.0],"Player_11":[60.0,7.0],"Player_11_video":[440.0,429.0],"Player_15":[73.0,38.0],"Player_15_video":[554.5,206.0],"Player_16":[62.0,40.0],"Player_16_video":[367.5,207.0],"Player_17":[82.0,31.0],"Player_17_video":[752.5,223.0],"Player_18":[74.0,55.0],"Player_18_video":[508.5,149.0],"Player_19":[61.0,26.0],"Player_19_video":[372.0,276.0],"Player_20":[53.0,43.0],"Player_20_video":[185.0,204.0],"Player_21":[49.0,21.0],"Player_21_video":[101.0,330.0],"Player_22":[78.0,19.0],"Player_22_video":[780.5,295.0],"Player_23":[80.0,24.0],"Player_23_video":[780.0,259.0],"Goalkeeper_14":[96.0,30.0],"Goalkeeper_14_video":[995.0,214.0],"Player_0":null,"Player_0_video":null,"Player_9":null,"Player_9_video":null,"Player_12":null,"Player_12_video":null,"Player_13":null,"Player_13_video":null,"Goalkeeper_5":[83.0,12.0],"Goalkeeper_5_video":[972.0,328.0],"Goalkeeper_8":[70.0,16.0],"Goalkeeper_8_video":[629.0,323.0],"Player_166":null,"Player_166_video":null,"Player_167":null,"Player_167_video":null,"Player_170":null,"Player_170_video":null,"Player_171":null,"Player_171_video":null,"Player_176":null,"Player_176_video":null,"Player_178":null,"Player_178_video":null,"Goalkeeper_172":null,"Goalkeeper_172_video":null,"Player_181":null,"Player_181_video":null,"Player_182":null,"Player_182_video":null,"Goalkeeper_196":null,"Goalkeeper_196_video":null,"Player_219":null,"Player_219_video":null,"Ball":[58.0,8.0],"Ball_video":[368.0,429.0]},{"Bottom_Left":[47.0,0],"Top_Left":[40.6830601093,68],"Top_Right":[123.2303030303,68],"Bottom_Right":[77.0727272727,0],"Player_1":[54.0,6.0],"Player_1_video":[247.0,459.0],"Player_2":[75.0,4.0],"Player_2_video":[886.0,418.0],"Player_3":[59.0,8.25],"Player_3_video":[397.875,425.5],"Player_4":[50.5,14.25],"Player_4_video":[149.25,381.0],"Player_6":[65.0,5.0],"Player_6_video":[605.0,443.0],"Player_7":[58.0,0.0],"Player_7_video":[423.5,522.0],"Player_10":[80.0,8.0],"Player_10_video":[956.125,367.5],"Player_11":[60.0,7.0],"Player_11_video":[444.5,427.0],"Player_15":[76.25,39.75],"Player_15_video":[596.0,196.75],"Player_16":[58.0,36.0],"Player_16_video":[349.8,230.2],"Player_17":[83.0,27.75],"Player_17_video":[803.5,239.25],"Player_18":null,"Player_18_video":null,"Player_19":[59.0,24.75],"Player_19_video":[332.375,287.5],"Player_20":[60.0,40.0],"Player_20_video":[325.875,209.5],"Player_21":[49.0,21.0],"Player_21_video":[116.0,330.0],"Player_22":[74.25,24.0],"Player_22_video":[681.375,273.75],"Player_23":null,"Player_23_video":null,"Goalkeeper_14":[90.25,31.25],"Goalkeeper_14_video":[889.0,214.25],"Player_0":null,"Player_0_video":null,"Player_9":null,"Player_9_video":null,"Player_12":null,"Player_12_video":null,"Player_13":null,"Player_13_video":null,"Goalkeeper_5":[77.6,11.8],"Goalkeeper_5_video":[901.5,342.4],"Goalkeeper_8":[70.0,16.0],"Goalkeeper_8_video":[641.5,324.0],"Player_166":null,"Player_166_video":null,"Player_167":null,"Player_167_video":null,"Player_170":null,"Player_170_video":null,"Player_171":null,"Player_171_video":null,"Player_176":null,"Player_176_video":null,"Player_178":null,"Player_178_video":null,"Goalkeeper_172":null,"Goalkeeper_172_video":null,"Player_181":null,"Player_181_video":null,"Player_182":null,"Player_182_video":null,"Goalkeeper_196":null,"Goalkeeper_196_video":null,"Player_219":null,"Player_219_video":null,"Ball":[54.0,10.0],"Ball_video":[261.0,419.0]},{"Bottom_Left":[47.0,0],"Top_Left":[40.6830601093,68],"Top_Right":[123.2303030303,68],"Bottom_Right":[77.0727272727,0],"Player_1":[54.2857142857,5.8571428571],"Player_1_video":[300.4285714286,459.2857142857],"Player_2":[71.3333333333,5.3333333333],"Player_2_video":[775.0,414.3333333333],"Player_3":[60.0,5.5],"Player_3_video":[445.25,455.0],"Player_4":[52.0,13.5],"Player_4_video":[194.0,383.0],"Player_6":[66.0,5.0],"Player_6_video":[616.5,437.0],"Player_7":[59.0,0.0],"Player_7_video":[446.0,519.0],"Player_10":[81.0,10.0],"Player_10_video":[949.75,351.0],"Player_11":[61.0,8.0],"Player_11_video":[459.5,420.0],"Player_15":[79.5,41.5],"Player_15_video":[637.5,187.5],"Player_16":[54.0,32.0],"Player_16_video":[332.1,253.4],"Player_17":[84.0,24.5],"Player_17_video":[854.5,255.5],"Player_18":null,"Player_18_video":null,"Player_19":[57.0,23.5],"Player_19_video":[292.75,299.0],"Player_20":[67.0,37.0],"Player_20_video":[466.75,215.0],"Player_21":[50.0,20.0],"Player_21_video":[132.0,331.0],"Player_22":[70.5,29.0],"Player_22_video":[582.25,252.5],"Player_23":null,"Player_23_video":null,"Goalkeeper_14":[84.5,32.5],"Goalkeeper_14_video":[783.0,214.5],"Player_0":null,"Player_0_video":null,"Player_9":null,"Player_9_video":null,"Player_12":null,"Player_12_video":null,"Player_13":null,"Player_13_video":null,"Goalkeeper_5":[72.2,11.6],"Goalkeeper_5_video":[831.0,356.8],"Goalkeeper_8":[72.6666666667,11.0],"Goalkeeper_8_video":[765.5,364.0],"Player_166":null,"Player_166_video":null,"Player_167":null,"Player_167_video":null,"Player_170":null,"Player_170_video":null,"Player_171":null,"Player_171_video":null,"Player_176":null,"Player_176_video":null,"Player_178":null,"Player_178_video":null,"Goalkeeper_172":null,"Goalkeeper_172_video":null,"Player_181":null,"Player_181_video":null,"Player_182":null,"Player_182_video":null,"Goalkeeper_196":null,"Goalkeeper_196_video":null,"Player_219":null,"Player_219_video":null,"Ball":[51.0,11.0],"Ball_video":[164.0,415.0]},{"Bottom_Left":[47.0,0],"Top_Left":[40.6830601093,68],"Top_Right":[123.2303030303,68],"Bottom_Right":[77.0727272727,0],"Player_1":[54.5714285714,5.7142857143],"Player_1_video":[353.8571428571,459.5714285714],"Player_2":[67.6666666667,6.6666666667],"Player_2_video":[664.0,410.6666666667],"Player_3":[61.0,2.75],"Player_3_video":[492.625,484.5],"Player_4":[53.5,12.75],"Player_4_video":[238.75,385.0],"Player_6":[66.0,5.0],"Player_6_video":[634.0,436.0],"Player_7":[56.5,9.5],"Player_7_video":[338.0,426.5],"Player_10":[82.0,12.0],"Player_10_video":[943.375,334.5],"Player_11":[64.5,6.0],"Player_11_video":[574.75,428.5],"Player_15":[82.75,43.25],"Player_15_video":[679.0,178.25],"Player_16":[50.0,28.0],"Player_16_video":[314.4,276.6],"Player_17":[85.0,21.25],"Player_17_video":[905.5,271.75],"Player_18":null,"Player_18_video":null,"Player_19":[55.0,22.25],"Player_19_video":[253.125,310.5],"Player_20":[74.0,34.0],"Player_20_video":[607.625,220.5],"Player_21":[62.5,17.0],"Player_21_video":[448.75,333.0],"Player_22":[66.75,34.0],"Player_22_video":[483.125,231.25],"Player_23":null,"Player_23_video":null,"Goalkeeper_14":[78.75,33.75],"Goalkeeper_14_video":[677.0,214.75],"Player_0":null,"Player_0_video":null,"Player_9":null,"Player_9_video":null,"Player_12":null,"Player_12_video":null,"Player_13":null,"Player_13_video":null,"Goalkeeper_5":[66.8,11.4],"Goalkeeper_5_video":[760.5,371.2],"Goalkeeper_8":[75.3333333333,6.0],"Goalkeeper_8_video":[889.5,404.0],"Player_166":null,"Player_166_video":null,"Player_167":null,"Player_167_video":null,"Player_170":null,"Player_170_video":null,"Player_171":null,"Player_171_video":null,"Player_176":null,"Player_176_video":null,"Player_178":null,"Player_178_video":null,"Goalkeeper_172":null,"Goalkeeper_172_video":null,"Player_181":null,"Player_181_video":null,"Player_182":null,"Player_182_video":null,"Goalkeeper_196":null,"Goalkeeper_196_video":null,"Player_219":null,"Player_219_video":null,"Ball":[50.0,11.5],"Ball_video":[122.25,412.5]},{"Bottom_Left":[47.0,0],"Top_Left":[40.6830601093,68],"Top_Right":[123.2303030303,68],"Bottom_Right":[77.0727272727,0],"Player_1":[54.8571428571,5.5714285714],"Player_1_video":[407.2857142857,459.8571428571],"Player_2":[64.0,8.0],"Player_2_video":[553.0,407.0],"Player_3":[62.0,0.0],"Player_3_video":[540.0,514.0],"Player_4":[55.0,12.0],"Player_4_video":[283.5,387.0],"Player_6":[63.0,8.0],"Player_6_video":[513.5,407.0],"Player_7":[54.0,19.0],"Player_7_video":[230.0,334.0],"Player_10":[83.0,14.0],"Player_10_video":[937.0,318.0],"Player_11":[68.0,4.0],"Player_11_video":[690.0,437.0],"Player_15":[86.0,45.0],"Player_15_video":[720.5,169.0],"Player_16":[46.0,24.0],"Player_16_video":[296.7,299.8],"Player_17":[86.0,18.0],"Player_17_video":[956.5,288.0],"Player_18":null,"Player_18_video":null,"Player_19":[53.0,21.0],"Player_19_video":[213.5,322.0],"Player_20":[81.0,31.0],"Player_20_video":[748.5,226.0],"Player_21":[75.0,14.0],"Player_21_video":[765.5,335.0],"Player_22":[63.0,39.0],"Player_22_video":[384.0,210.0],"Player_23":null,"Player_23_video":null,"Goalkeeper_14":[73.0,35.0],"Goalkeeper_14_video":[571.0,215.0],"Player_0":[58.0,6.0],"Player_0_video":[381.5,445.0],"Player_9":[90.0,24.0],"Player_9_video":[960.0,245.0],"Player_12":[68.0,22.0],"Player_12_video":[539.5,290.0],"Player_13":[56.0,0.0],"Player_13_video":[357.0,546.0],"Goalkeeper_5":[61.4,11.2],"Goalkeeper_5_video":[690.0,385.6],"Goalkeeper_8":[78.0,1.0],"Goalkeeper_8_video":[1013.5,444.0],"Player_166":null,"Player_166_video":null,"Player_167":null,"Player_167_video":null,"Player_170":null,"Player_170_video":null,"Player_171":null,"Player_171_video":null,"Player_176":null,"Player_176_video":null,"Player_178":null,"Player_178_video":null,"Goalkeeper_172":null,"Goalkeeper_172_video":null,"Player_181":null,"Player_181_video":null,"Player_182":null,"Player_182_video":null,"Goalkeeper_196":null,"Goalkeeper_196_video":null,"Player_219":null,"Player_219_video":null,"Ball":[49.0,12.0],"Ball_video":[80.5,410.0]},{"Bottom_Left":[37.231372549,0],"Top_Left":[11.0980392157,68],"Top_Right":[95.2456140351,68],"Bottom_Right":[67.8070175439,0],"Player_1":[55.1428571429,5.4285714286],"Player_1_video":[460.7142857143,460.1428571429],"Player_2":[61.6,9.6],"Player_2_video":[545.2,396.0],"Player_3":[50.0,6.0],"Player_3_video":[445.0,446.0],"Player_4":[61.0,6.0],"Player_4_video":[745.5,444.0],"Player_6":[66.0,17.0],"Player_6_video":[830.5,345.0],"Player_7":[55.0,9.0],"Player_7_video":[579.0,414.0],"Player_10":[75.0,18.0],"Player_10_video":[1009.0,337.0],"Player_11":[57.0,24.0],"Player_11_video":[610.5,300.0],"Player_15":[49.0,42.0],"Player_15_video":[461.0,216.0],"Player_16":[42.0,20.0],"Player_16_video":[279.0,323.0],"Player_17":[81.6,21.6],"Player_17_video":[907.0,278.4],"Player_18":null,"Player_18_video":null,"Player_19":[50.0,0.0],"Player_19_video":[434.5,543.0],"Player_20":null,"Player_20_video":null,"Player_21":null,"Player_21_video":null,"Player_22":null,"Player_22_video":null,"Player_23":null,"Player_23_video":null,"Goalkeeper_14":[71.0,36.0],"Goalkeeper_14_video":[828.0,240.0],"Player_0":[55.0,1.0],"Player_0_video":[601.0,517.0],"Player_9":[74.0,54.0],"Player_9_video":[805.0,180.0],"Player_12":[43.0,18.0],"Player_12_video":[295.0,339.0],"Player_13":[61.0,39.0],"Player_13_video":[650.5,227.0],"Goalkeeper_5":[56.0,11.0],"Goalkeeper_5_video":[619.5,400.0],"Goalkeeper_8":[46.0,11.0],"Goalkeeper_8_video":[345.0,393.0],"Player_166":null,"Player_166_video":null,"Player_167":null,"Player_167_video":null,"Player_170":null,"Player_170_video":null,"Player_171":null,"Player_171_video":null,"Player_176":null,"Player_176_video":null,"Player_178":null,"Player_178_video":null,"Goalkeeper_172":null,"Goalkeeper_172_video":null,"Player_181":null,"Player_181_video":null,"Player_182":null,"Player_182_video":null,"Goalkeeper_196":null,"Goalkeeper_196_video":null,"Player_219":null,"Player_219_video":null,"Ball":[36.0,10.0],"Ball_video":[85.5,409.0]},{"Bottom_Left":[37.231372549,0],"Top_Left":[11.0980392157,68],"Top_Right":[95.2456140351,68],"Bottom_Right":[67.8070175439,0],"Player_1":[55.4285714286,5.2857142857],"Player_1_video":[514.1428571429,460.4285714286],"Player_2":[59.2,11.2],"Player_2_video":[537.4,385.0],"Player_3":[54.6666666667,7.0],"Player_3_video":[570.5,435.6666666667],"Player_4":[57.3333333333,9.6666666667],"Player_4_video":[653.0,412.6666666667],"Player_6":[57.0,8.0],"Player_6_video":[648.5,425.0],"Player_7":[58.6666666667,12.6666666667],"Player_7_video":[656.5,384.6666666667],"Player_10":[73.0,16.0],"Player_10_video":[989.25,354.0],"Player_11":[62.3333333333,27.0],"Player_11_video":[699.8333333333,284.6666666667],"Player_15":null,"Player_15_video":null,"Player_16":null,"Player_16_video":null,"Player_17":[77.2,25.2],"Player_17_video":[857.5,268.8],"Player_18":null,"Player_18_video":null,"Player_19":[48.4,1.7333333333],"Player_19_video":[432.6333333333,525.3333333333],"Player_20":null,"Player_20_video":null,"Player_21":null,"Player_21_video":null,"Player_22":null,"Player_22_video":null,"Player_23":null,"Player_23_video":null,"Goalkeeper_14":[64.6666666667,27.6666666667],"Goalkeeper_14_video":[720.5,293.6666666667],"Player_0":[56.6666666667,0.6666666667],"Player_0_video":[661.1666666667,525.0],"Player_9":[65.6666666667,42.6666666667],"Player_9_video":[679.6666666667,229.3333333333],"Player_12":[49.0,24.3333333333],"Player_12_video":[415.6666666667,305.0],"Player_13":null,"Player_13_video":null,"Goalkeeper_5":[47.6666666667,15.6666666667],"Goalkeeper_5_video":[440.1666666667,365.0],"Goalkeeper_8":[52.6666666667,8.6666666667],"Goalkeeper_8_video":[534.1666666667,418.6666666667],"Player_166":null,"Player_166_video":null,"Player_167":null,"Player_167_video":null,"Player_170":null,"Player_170_video":null,"Player_171":null,"Player_171_video":null,"Player_176":null,"Player_176_video":null,"Player_178":null,"Player_178_video":null,"Goalkeeper_172":null,"Goalkeeper_172_video":null,"Player_181":null,"Player_181_video":null,"Player_182":null,"Player_182_video":null,"Goalkeeper_196":null,"Goalkeeper_196_video":null,"Player_219":null,"Player_219_video":null,"Ball":[36.0,12.0],"Ball_video":[111.0,386.0]},{"Bottom_Left":[37.231372549,0],"Top_Left":[11.0980392157,68],"Top_Right":[95.2456140351,68],"Bottom_Right":[67.8070175439,0],"Player_1":[55.7142857143,5.1428571429],"Player_1_video":[567.5714285714,460.7142857143],"Player_2":[56.8,12.8],"Player_2_video":[529.6,374.0],"Player_3":[59.3333333333,8.0],"Player_3_video":[696.0,425.3333333333],"Player_4":[53.6666666667,13.3333333333],"Player_4_video":[560.5,381.3333333333],"Player_6":[56.0833333333,8.25],"Player_6_video":[656.75,424.5],"Player_7":[62.3333333333,16.3333333333],"Player_7_video":[734.0,355.3333333333],"Player_10":[71.0,14.0],"Player_10_video":[969.5,371.0],"Player_11":[67.6666666667,30.0],"Player_11_video":[789.1666666667,269.3333333333],"Player_15":null,"Player_15_video":null,"Player_16":null,"Player_16_video":null,"Player_17":[72.8,28.8],"Player_17_video":[808.0,259.2],"Player_18":null,"Player_18_video":null,"Player_19":[46.8,3.4666666667],"Player_19_video":[430.7666666667,507.6666666667],"Player_20":null,"Player_20_video":null,"Player_21":null,"Player_21_video":null,"Player_22":null,"Player_22_video":null,"Player_23":null,"Player_23_video":null,"Goalkeeper_14":[58.3333333333,19.3333333333],"Goalkeeper_14_video":[613.0,347.3333333333],"Player_0":[58.3333333333,0.3333333333],"Player_0_video":[721.3333333333,533.0],"Player_9":[57.3333333333,31.3333333333],"Player_9_video":[554.3333333333,278.6666666667],"Player_12":[55.0,30.6666666667],"Player_12_video":[536.3333333333,271.0],"Player_13":null,"Player_13_video":null,"Goalkeeper_5":[39.3333333333,20.3333333333],"Goalkeeper_5_video":[260.8333333333,330.0],"Goalkeeper_8":[59.3333333333,6.3333333333],"Goalkeeper_8_video":[723.3333333333,444.3333333333],"Player_166":null,"Player_166_video":null,"Player_167":null,"Player_167_video":null,"Player_170":null,"Player_170_video":null,"Player_171":null,"Player_171_video":null,"Player_176":null,"Player_176_video":null,"Player_178":null,"Player_178_video":null,"Goalkeeper_172":null,"Goalkeeper_172_video":null,"Player_181":null,"Player_181_video":null,"Player_182":null,"Player_182_video":null,"Goalkeeper_196":null,"Goalkeeper_196_video":null,"Player_219":null,"Player_219_video":null,"Ball":[37.0,14.0],"Ball_video":[131.5,374.0]},{"Bottom_Left":[37.231372549,0],"Top_Left":[11.0980392157,68],"Top_Right":[95.2456140351,68],"Bottom_Right":[67.8070175439,0],"Player_1":[56.0,5.0],"Player_1_video":[621.0,461.0],"Player_2":[54.4,14.4],"Player_2_video":[521.8,363.0],"Player_3":[64.0,9.0],"Player_3_video":[821.5,415.0],"Player_4":[50.0,17.0],"Player_4_video":[468.0,350.0],"Player_6":[55.1666666667,8.5],"Player_6_video":[665.0,424.0],"Player_7":[66.0,20.0],"Player_7_video":[811.5,326.0],"Player_10":[61.0,6.0],"Player_10_video":[759.0,445.0],"Player_11":[73.0,33.0],"Player_11_video":[878.5,254.0],"Player_15":null,"Player_15_video":null,"Player_16":null,"Player_16_video":null,"Player_17":[68.4,32.4],"Player_17_video":[758.5,249.6],"Player_18":null,"Player_18_video":null,"Player_19":[45.2,5.2],"Player_19_video":[428.9,490.0],"Player_20":null,"Player_20_video":null,"Player_21":null,"Player_21_video":null,"Player_22":null,"Player_22_video":null,"Player_23":null,"Player_23_video":null,"Goalkeeper_14":[52.0,11.0],"Goalkeeper_14_video":[505.5,401.0],"Player_0":[60.0,0.0],"Player_0_video":[781.5,541.0],"Player_9":[49.0,20.0],"Player_9_video":[429.0,328.0],"Player_12":[61.0,37.0],"Player_12_video":[657.0,237.0],"Player_13":null,"Player_13_video":null,"Goalkeeper_5":[31.0,25.0],"Goalkeeper_5_video":[81.5,295.0],"Goalkeeper_8":[66.0,4.0],"Goalkeeper_8_video":[912.5,470.0],"Player_166":null,"Player_166_video":null,"Player_167":null,"Player_167_video":null,"Player_170":null,"Player_170_video":null,"Player_171":null,"Player_171_video":null,"Player_176":null,"Player_176_video":null,"Player_178":null,"Player_178_video":null,"Goalkeeper_172":null,"Goalkeeper_172_video":null,"Player_181":null,"Player_181_video":null,"Player_182":null,"Player_182_video":null,"Goalkeeper_196":null,"Goalkeeper_196_video":null,"Player_219":null,"Player_219_video":null,"Ball":[37.5,15.5],"Ball_video":[155.0,361.5]},{"Bottom_Left":[37.231372549,0],"Top_Left":[11.0980392157,68],"Top_Right":[95.2456140351,68],"Bottom_Right":[67.8070175439,0],"Player_1":[63.0,6.0],"Player_1_video":[807.0,449.0],"Player_2":[52.0,16.0],"Player_2_video":[514.0,352.0],"Player_3":[62.0,0.0],"Player_3_video":[834.5,549.0],"Player_4":[58.0,5.0],"Player_4_video":[669.5,466.0],"Player_6":[54.25,8.75],"Player_6_video":[673.25,423.5],"Player_7":[54.0,10.0],"Player_7_video":[544.5,403.0],"Player_10":[50.0,19.0],"Player_10_video":[467.5,331.0],"Player_11":[76.0,32.0],"Player_11_video":[945.5,260.0],"Player_15":null,"Player_15_video":null,"Player_16":null,"Player_16_video":null,"Player_17":[64.0,36.0],"Player_17_video":[709.0,240.0],"Player_18":null,"Player_18_video":null,"Player_19":[43.6,6.9333333333],"Player_19_video":[427.0333333333,472.3333333333],"Player_20":null,"Player_20_video":null,"Player_21":null,"Player_21_video":null,"Player_22":null,"Player_22_video":null,"Player_23":null,"Player_23_video":null,"Goalkeeper_14":null,"Goalkeeper_14_video":null,"Player_0":[67.0,4.0],"Player_0_video":[962.0,477.0],"Player_9":[69.0,19.0],"Player_9_video":[872.0,331.0],"Player_12":[56.3333333333,34.6666666667],"Player_12_video":[624.0,249.3333333333],"Player_13":null,"Player_13_video":null,"Goalkeeper_5":[66.0,9.0],"Goalkeeper_5_video":[882.0,417.0],"Goalkeeper_8":[34.0,24.0],"Goalkeeper_8_video":[137.0,296.0],"Player_166":null,"Player_166_video":null,"Player_167":null,"Player_167_video":null,"Player_170":null,"Player_170_video":null,"Player_171":null,"Player_171_video":null,"Player_176":null,"Player_176_video":null,"Player_178":null,"Player_178_video":null,"Goalkeeper_172":null,"Goalkeeper_172_video":null,"Player_181":null,"Player_181_video":null,"Player_182":null,"Player_182_video":null,"Goalkeeper_196":null,"Goalkeeper_196_video":null,"Player_219":null,"Player_219_video":null,"Ball":[38.0,17.0],"Ball_video":[178.5,349.0]},{"Bottom_Left":[23.6109589041,0],"Top_Left":[-28.7397260274,68],"Top_Right":[63.1497584541,68],"Bottom_Right":[56.9082125604,0],"Player_1":null,"Player_1_video":null,"Player_2":[55.0,13.0],"Player_2_video":[928.0,421.0],"Player_3":null,"Player_3_video":null,"Player_4":null,"Player_4_video":null,"Player_6":[53.3333333333,9.0],"Player_6_video":[681.5,423.0],"Player_7":null,"Player_7_video":null,"Player_10":null,"Player_10_video":null,"Player_11":[67.0,27.0],"Player_11_video":[846.75,294.0],"Player_15":null,"Player_15_video":null,"Player_16":null,"Player_16_video":null,"Player_17":null,"Player_17_video":null,"Player_18":null,"Player_18_video":null,"Player_19":[42.0,8.6666666667],"Player_19_video":[425.1666666667,454.6666666667],"Player_20":null,"Player_20_video":null,"Player_21":null,"Player_21_video":null,"Player_22":null,"Player_22_video":null,"Player_23":null,"Player_23_video":null,"Goalkeeper_14":null,"Goalkeeper_14_video":null,"Player_0":null,"Player_0_video":null,"Player_9":null,"Player_9_video":null,"Player_12":[51.6666666667,32.3333333333],"Player_12_video":[591.0,261.6666666667],"Player_13":null,"Player_13_video":null,"Goalkeeper_5":null,"Goalkeeper_5_video":null,"Goalkeeper_8":null,"Goalkeeper_8_video":null,"Player_166":null,"Player_166_video":null,"Player_167":null,"Player_167_video":null,"Player_170":null,"Player_170_video":null,"Player_171":null,"Player_171_video":null,"Player_176":null,"Player_176_video":null,"Player_178":null,"Player_178_video":null,"Goalkeeper_172":null,"Goalkeeper_172_video":null,"Player_181":null,"Player_181_video":null,"Player_182":null,"Player_182_video":null,"Goalkeeper_196":null,"Goalkeeper_196_video":null,"Player_219":null,"Player_219_video":null,"Ball":[22.0,15.0],"Ball_video":[194.0,339.0]},{"Bottom_Left":[23.6109589041,0],"Top_Left":[-28.7397260274,68],"Top_Right":[63.1497584541,68],"Bottom_Right":[56.9082125604,0],"Player_1":null,"Player_1_video":null,"Player_2":[55.5,13.5],"Player_2_video":[943.5,419.5],"Player_3":null,"Player_3_video":null,"Player_4":null,"Player_4_video":null,"Player_6":[52.4166666667,9.25],"Player_6_video":[689.75,422.5],"Player_7":null,"Player_7_video":null,"Player_10":null,"Player_10_video":null,"Player_11":[58.0,22.0],"Player_11_video":[748.0,328.0],"Player_15":null,"Player_15_video":null,"Player_16":null,"Player_16_video":null,"Player_17":null,"Player_17_video":null,"Player_18":null,"Player_18_video":null,"Player_19":[40.4,10.4],"Player_19_video":[423.3,437.0],"Player_20":null,"Player_20_video":null,"Player_21":null,"Player_21_video":null,"Player_22":null,"Player_22_video":null,"Player_23":null,"Player_23_video":null,"Goalkeeper_14":null,"Goalkeeper_14_video":null,"Player_0":null,"Player_0_video":null,"Player_9":null,"Player_9_video":null,"Player_12":[47.0,30.0],"Player_12_video":[558.0,274.0],"Player_13":null,"Player_13_video":null,"Goalkeeper_5":null,"Goalkeeper_5_video":null,"Goalkeeper_8":null,"Goalkeeper_8_video":null,"Player_166":[48.0,6.0],"Player_166_video":[713.0,471.0],"Player_167":[57.0,8.0],"Player_167_video":[999.0,479.0],"Player_170":[35.0,21.0],"Player_170_video":[491.5,324.0],"Player_171":[39.0,17.0],"Player_171_video":[555.5,352.0],"Player_176":[41.0,11.0],"Player_176_video":[571.5,401.0],"Player_178":[52.0,9.0],"Player_178_video":[841.5,450.0],"Goalkeeper_172":[18.0,21.0],"Goalkeeper_172_video":[178.5,297.0],"Player_181":null,"Player_181_video":null,"Player_182":null,"Player_182_video":null,"Goalkeeper_196":null,"Goalkeeper_196_video":null,"Player_219":null,"Player_219_video":null,"Ball":[21.0,16.0],"Ball_video":[188.5,329.0]},{"Bottom_Left":[23.6109589041,0],"Top_Left":[-28.7397260274,68],"Top_Right":[63.1497584541,68],"Bottom_Right":[56.9082125604,0],"Player_1":null,"Player_1_video":null,"Player_2":[56.0,14.0],"Player_2_video":[959.0,418.0],"Player_3":null,"Player_3_video":null,"Player_4":null,"Player_4_video":null,"Player_6":[51.5,9.5],"Player_6_video":[698.0,422.0],"Player_7":null,"Player_7_video":null,"Player_10":null,"Player_10_video":null,"Player_11":[49.0,17.0],"Player_11_video":[649.25,362.0],"Player_15":null,"Player_15_video":null,"Player_16":null,"Player_16_video":null,"Player_17":null,"Player_17_video":null,"Player_18":null,"Player_18_video":null,"Player_19":[38.8,12.1333333333],"Player_19_video":[421.4333333333,419.3333333333],"Player_20":null,"Player_20_video":null,"Player_21":null,"Player_21_video":null,"Player_22":null,"Player_22_video":null,"Player_23":null,"Player_23_video":null,"Goalkeeper_14":null,"Goalkeeper_14_video":null,"Player_0":null,"Player_0_video":null,"Player_9":null,"Player_9_video":null,"Player_12":[42.3333333333,27.6666666667],"Player_12_video":[525.0,286.3333333333],"Player_13":null,"Player_13_video":null,"Goalkeeper_5":null,"Goalkeeper_5_video":null,"Goalkeeper_8":null,"Goalkeeper_8_video":null,"Player_166":[48.0,6.0],"Player_166_video":[717.0,472.0],"Player_167":[57.0,9.0],"Player_167_video":[995.5,473.0],"Player_170":null,"Player_170_video":null,"Player_171":[39.0,18.0],"Player_171_video":[558.0,351.0],"Player_176":null,"Player_176_video":null,"Player_178":null,"Player_178_video":null,"Goalkeeper_172":null,"Goalkeeper_172_video":null,"Player_181":[54.0,1.0],"Player_181_video":[897.0,560.0],"Player_182":[56.0,24.0],"Player_182_video":[945.5,339.0],"Goalkeeper_196":null,"Goalkeeper_196_video":null,"Player_219":null,"Player_219_video":null,"Ball":[20.0,17.0],"Ball_video":[177.5,320.0]},{"Bottom_Left":[23.6109589041,0],"Top_Left":[-28.7397260274,68],"Top_Right":[63.1497584541,68],"Bottom_Right":[56.9082125604,0],"Player_1":null,"Player_1_video":null,"Player_2":[57.0,14.0],"Player_2_video":[969.5,417.0],"Player_3":null,"Player_3_video":null,"Player_4":null,"Player_4_video":null,"Player_6":[50.5833333333,9.75],"Player_6_video":[706.25,421.5],"Player_7":null,"Player_7_video":null,"Player_10":null,"Player_10_video":null,"Player_11":[40.0,12.0],"Player_11_video":[550.5,396.0],"Player_15":null,"Player_15_video":null,"Player_16":null,"Player_16_video":null,"Player_17":null,"Player_17_video":null,"Player_18":null,"Player_18_video":null,"Player_19":[37.2,13.8666666667],"Player_19_video":[419.5666666667,401.6666666667],"Player_20":null,"Player_20_video":null,"Player_21":null,"Player_21_video":null,"Player_22":null,"Player_22_video":null,"Player_23":null,"Player_23_video":null,"Goalkeeper_14":null,"Goalkeeper_14_video":null,"Player_0":null,"Player_0_video":null,"Player_9":null,"Player_9_video":null,"Player_12":[37.6666666667,25.3333333333],"Player_12_video":[492.0,298.6666666667],"Player_13":null,"Player_13_video":null,"Goalkeeper_5":null,"Goalkeeper_5_video":null,"Goalkeeper_8":null,"Goalkeeper_8_video":null,"Player_166":[48.0,6.0],"Player_166_video":[714.5,472.0],"Player_167":[57.0,9.0],"Player_167_video":[985.5,468.0],"Player_170":null,"Player_170_video":null,"Player_171":[39.0,18.0],"Player_171_video":[554.5,350.0],"Player_176":null,"Player_176_video":null,"Player_178":null,"Player_178_video":null,"Goalkeeper_172":null,"Goalkeeper_172_video":null,"Player_181":[54.0,1.0],"Player_181_video":[898.5,558.0],"Player_182":[56.0,25.0],"Player_182_video":[947.0,339.0],"Goalkeeper_196":null,"Goalkeeper_196_video":null,"Player_219":null,"Player_219_video":null,"Ball":[19.0,18.0],"Ball_video":[167.5,313.0]},{"Bottom_Left":[23.6109589041,0],"Top_Left":[-28.7397260274,68],"Top_Right":[63.1497584541,68],"Bottom_Right":[56.9082125604,0],"Player_1":null,"Player_1_video":null,"Player_2":[57.0,15.0],"Player_2_video":[973.5,414.0],"Player_3":null,"Player_3_video":null,"Player_4":null,"Player_4_video":null,"Player_6":[49.6666666667,10.0],"Player_6_video":[714.5,421.0],"Player_7":null,"Player_7_video":null,"Player_10":null,"Player_10_video":null,"Player_11":null,"Player_11_video":null,"Player_15":null,"Player_15_video":null,"Player_16":null,"Player_16_video":null,"Player_17":null,"Player_17_video":null,"Player_18":null,"Player_18_video":null,"Player_19":[35.6,15.6],"Player_19_video":[417.7,384.0],"Player_20":null,"Player_20_video":null,"Player_21":null,"Player_21_video":null,"Player_22":null,"Player_22_video":null,"Player_23":null,"Player_23_video":null,"Goalkeeper_14":null,"Goalkeeper_14_video":null,"Player_0":null,"Player_0_video":null,"Player_9":null,"Player_9_video":null,"Player_12":[33.0,23.0],"Player_12_video":[459.0,311.0],"Player_13":null,"Player_13_video":null,"Goalkeeper_5":null,"Goalkeeper_5_video":null,"Goalkeeper_8":null,"Goalkeeper_8_video":null,"Player_166":[48.0,6.0],"Player_166_video":[708.5,471.0],"Player_167":[56.0,10.0],"Player_167_video":[973.5,462.0],"Player_170":null,"Player_170_video":null,"Player_171":[39.0,18.0],"Player_171_video":[548.5,349.0],"Player_176":null,"Player_176_video":null,"Player_178":null,"Player_178_video":null,"Goalkeeper_172":null,"Goalkeeper_172_video":null,"Player_181":[54.0,1.0],"Player_181_video":[893.0,557.0],"Player_182":[56.0,25.0],"Player_182_video":[946.0,339.0],"Goalkeeper_196":null,"Goalkeeper_196_video":null,"Player_219":null,"Player_219_video":null,"Ball":[18.25,18.25],"Ball_video":[166.375,310.0]},{"Bottom_Left":[22.1890410959,0],"Top_Left":[-34.2602739726,68],"Top_Right":[60.2824742268,68],"Bottom_Right":[55.9360824742,0],"Player_1":null,"Player_1_video":null,"Player_2":[55.0,15.0],"Player_2_video":[972.0,412.0],"Player_3":null,"Player_3_video":null,"Player_4":null,"Player_4_video":null,"Player_6":[48.75,10.25],"Player_6_video":[722.75,420.5],"Player_7":null,"Player_7_video":null,"Player_10":null,"Player_10_video":null,"Player_11":null,"Player_11_video":null,"Player_15":null,"Player_15_video":null,"Player_16":null,"Player_16_video":null,"Player_17":null,"Player_17_video":null,"Player_18":null,"Player_18_video":null,"Player_19":[34.0,17.3333333333],"Player_19_video":[415.8333333333,366.3333333333],"Player_20":null,"Player_20_video":null,"Player_21":null,"Player_21_video":null,"Player_22":null,"Player_22_video":null,"Player_23":null,"Player_23_video":null,"Goalkeeper_14":null,"Goalkeeper_14_video":null,"Player_0":null,"Player_0_video":null,"Player_9":null,"Player_9_video":null,"Player_12":null,"Player_12_video":null,"Player_13":null,"Player_13_video":null,"Goalkeeper_5":null,"Goalkeeper_5_video":null,"Goalkeeper_8":null,"Goalkeeper_8_video":null,"Player_166":[45.0,6.0],"Player_166_video":[701.5,470.0],"Player_167":[54.0,10.0],"Player_167_video":[957.5,454.0],"Player_170":null,"Player_170_video":null,"Player_171":[36.0,17.0],"Player_171_video":[539.5,348.0],"Player_176":null,"Player_176_video":null,"Player_178":null,"Player_178_video":null,"Goalkeeper_172":null,"Goalkeeper_172_video":null,"Player_181":[52.0,1.0],"Player_181_video":[886.5,556.0],"Player_182":[54.0,25.0],"Player_182_video":[943.0,336.0],"Goalkeeper_196":[15.0,18.0],"Goalkeeper_196_video":[151.0,302.0],"Player_219":null,"Player_219_video":null,"Ball":[17.5,18.5],"Ball_video":[165.25,307.0]},{"Bottom_Left":[22.1890410959,0],"Top_Left":[-34.2602739726,68],"Top_Right":[60.2824742268,68],"Bottom_Right":[55.9360824742,0],"Player_1":null,"Player_1_video":null,"Player_2":[54.0,15.0],"Player_2_video":[969.5,407.0],"Player_3":null,"Player_3_video":null,"Player_4":null,"Player_4_video":null,"Player_6":[47.8333333333,10.5],"Player_6_video":[731.0,420.0],"Player_7":null,"Player_7_video":null,"Player_10":null,"Player_10_video":null,"Player_11":null,"Player_11_video":null,"Player_15":null,"Player_15_video":null,"Player_16":null,"Player_16_video":null,"Player_17":null,"Player_17_video":null,"Player_18":null,"Player_18_video":null,"Player_19":[32.4,19.0666666667],"Player_19_video":[413.9666666667,348.6666666667],"Player_20":null,"Player_20_video":null,"Player_21":null,"Player_21_video":null,"Player_22":null,"Player_22_video":null,"Player_23":null,"Player_23_video":null,"Goalkeeper_14":null,"Goalkeeper_14_video":null,"Player_0":null,"Player_0_video":null,"Player_9":null,"Player_9_video":null,"Player_12":null,"Player_12_video":null,"Player_13":null,"Player_13_video":null,"Goalkeeper_5":null,"Goalkeeper_5_video":null,"Goalkeeper_8":null,"Goalkeeper_8_video":null,"Player_166":[45.0,6.0],"Player_166_video":[692.0,469.0],"Player_167":[54.0,11.0],"Player_167_video":[945.0,447.0],"Player_170":null,"Player_170_video":null,"Player_171":[36.0,18.0],"Player_171_video":[531.5,345.0],"Player_176":null,"Player_176_video":null,"Player_178":null,"Player_178_video":null,"Goalkeeper_172":null,"Goalkeeper_172_video":null,"Player_181":[52.0,1.0],"Player_181_video":[880.0,554.0],"Player_182":[53.0,25.0],"Player_182_video":[937.5,334.0],"Goalkeeper_196":[15.0,18.0],"Goalkeeper_196_video":[143.0,302.0],"Player_219":null,"Player_219_video":null,"Ball":[16.75,18.75],"Ball_video":[164.125,304.0]},{"Bottom_Left":[22.1890410959,0],"Top_Left":[-34.2602739726,68],"Top_Right":[60.2824742268,68],"Bottom_Right":[55.9360824742,0],"Player_1":null,"Player_1_video":null,"Player_2":[54.0,16.0],"Player_2_video":[967.5,402.0],"Player_3":null,"Player_3_video":null,"Player_4":null,"Player_4_video":null,"Player_6":[46.9166666667,10.75],"Player_6_video":[739.25,419.5],"Player_7":null,"Player_7_video":null,"Player_10":null,"Player_10_video":null,"Player_11":null,"Player_11_video":null,"Player_15":null,"Player_15_video":null,"Player_16":null,"Player_16_video":null,"Player_17":null,"Player_17_video":null,"Player_18":null,"Player_18_video":null,"Player_19":[30.8,20.8],"Player_19_video":[412.1,331.0],"Player_20":null,"Player_20_video":null,"Player_21":null,"Player_21_video":null,"Player_22":null,"Player_22_video":null,"Player_23":null,"Player_23_video":null,"Goalkeeper_14":null,"Goalkeeper_14_video":null,"Player_0":null,"Player_0_video":null,"Player_9":null,"Player_9_video":null,"Player_12":null,"Player_12_video":null,"Player_13":null,"Player_13_video":null,"Goalkeeper_5":null,"Goalkeeper_5_video":null,"Goalkeeper_8":null,"Goalkeeper_8_video":null,"Player_166":[45.0,6.0],"Player_166_video":[685.0,467.0],"Player_167":[53.0,12.0],"Player_167_video":[933.0,437.0],"Player_170":null,"Player_170_video":null,"Player_171":[35.0,18.0],"Player_171_video":[524.5,343.0],"Player_176":null,"Player_176_video":null,"Player_178":null,"Player_178_video":null,"Goalkeeper_172":null,"Goalkeeper_172_video":null,"Player_181":[51.0,2.0],"Player_181_video":[869.5,549.0],"Player_182":[53.0,26.0],"Player_182_video":[932.5,331.0],"Goalkeeper_196":[14.0,18.0],"Goalkeeper_196_video":[136.5,301.0],"Player_219":null,"Player_219_video":null,"Ball":[16.0,19.0],"Ball_video":[163.0,301.0]},{"Bottom_Left":[22.1890410959,0],"Top_Left":[-34.2602739726,68],"Top_Right":[60.2824742268,68],"Bottom_Right":[55.9360824742,0],"Player_1":null,"Player_1_video":null,"Player_2":[54.0,17.0],"Player_2_video":[967.5,397.0],"Player_3":null,"Player_3_video":null,"Player_4":null,"Player_4_video":null,"Player_6":[46.0,11.0],"Player_6_video":[747.5,419.0],"Player_7":null,"Player_7_video":null,"Player_10":null,"Player_10_video":null,"Player_11":null,"Player_11_video":null,"Player_15":null,"Player_15_video":null,"Player_16":null,"Player_16_video":null,"Player_17":null,"Player_17_video":null,"Player_18":null,"Player_18_video":null,"Player_19":[29.2,22.5333333333],"Player_19_video":[410.2333333333,313.3333333333],"Player_20":null,"Player_20_video":null,"Player_21":null,"Player_21_video":null,"Player_22":null,"Player_22_video":null,"Player_23":null,"Player_23_video":null,"Goalkeeper_14":null,"Goalkeeper_14_video":null,"Player_0":null,"Player_0_video":null,"Player_9":null,"Player_9_video":null,"Player_12":null,"Player_12_video":null,"Player_13":null,"Player_13_video":null,"Goalkeeper_5":null,"Goalkeeper_5_video":null,"Goalkeeper_8":null,"Goalkeeper_8_video":null,"Player_166":[45.0,6.0],"Player_166_video":[677.0,464.0],"Player_167":[53.0,12.0],"Player_167_video":[921.5,430.0],"Player_170":null,"Player_170_video":null,"Player_171":[35.0,18.0],"Player_171_video":[519.0,340.0],"Player_176":null,"Player_176_video":null,"Player_178":null,"Player_178_video":null,"Goalkeeper_172":null,"Goalkeeper_172_video":null,"Player_181":[51.0,2.0],"Player_181_video":[862.0,545.0],"Player_182":[53.0,26.0],"Player_182_video":[928.0,328.0],"Goalkeeper_196":[14.0,19.0],"Goalkeeper_196_video":[132.5,299.0],"Player_219":[57.0,42.0],"Player_219_video":[1009.0,259.0],"Ball":[16.0,19.5],"Ball_video":[167.75,298.5]},{"Bottom_Left":[22.1890410959,0],"Top_Left":[-34.2602739726,68],"Top_Right":[60.2824742268,68],"Bottom_Right":[55.9360824742,0],"Player_1":null,"Player_1_video":null,"Player_2":[54.0,17.0],"Player_2_video":[966.0,393.0],"Player_3":null,"Player_3_video":null,"Player_4":null,"Player_4_video":null,"Player_6":null,"Player_6_video":null,"Player_7":null,"Player_7_video":null,"Player_10":null,"Player_10_video":null,"Player_11":null,"Player_11_video":null,"Player_15":null,"Player_15_video":null,"Player_16":null,"Player_16_video":null,"Player_17":null,"Player_17_video":null,"Player_18":null,"Player_18_video":null,"Player_19":[27.6,24.2666666667],"Player_19_video":[408.3666666667,295.6666666667],"Player_20":null,"Player_20_video":null,"Player_21":null,"Player_21_video":null,"Player_22":null,"Player_22_video":null,"Player_23":null,"Player_23_video":null,"Goalkeeper_14":null,"Goalkeeper_14_video":null,"Player_0":null,"Player_0_video":null,"Player_9":null,"Player_9_video":null,"Player_12":null,"Player_12_video":null,"Player_13":null,"Player_13_video":null,"Goalkeeper_5":null,"Goalkeeper_5_video":null,"Goalkeeper_8":null,"Goalkeeper_8_video":null,"Player_166":[44.0,6.0],"Player_166_video":[668.0,462.0],"Player_167":[52.0,13.0],"Player_167_video":[911.5,420.0],"Player_170":null,"Player_170_video":null,"Player_171":[35.0,18.0],"Player_171_video":[515.0,338.0],"Player_176":null,"Player_176_video":null,"Player_178":null,"Player_178_video":null,"Goalkeeper_172":null,"Goalkeeper_172_video":null,"Player_181":[51.0,2.0],"Player_181_video":[855.0,542.0],"Player_182":[53.0,27.0],"Player_182_video":[922.0,325.0],"Goalkeeper_196":[14.0,19.0],"Goalkeeper_196_video":[132.5,297.0],"Player_219":[57.0,43.0],"Player_219_video":[1004.5,257.0],"Ball":[16.0,20.0],"Ball_video":[172.5,296.0]},{"Bottom_Left":[21.4620689655,0],"Top_Left":[-34.1103448276,68],"Top_Right":[59.5366568915,68],"Bottom_Right":[55.9472140762,0],"Player_1":null,"Player_1_video":null,"Player_2":[55.0,17.0],"Player_2_video":[962.0,389.0],"Player_3":null,"Player_3_video":null,"Player_4":null,"Player_4_video":null,"Player_6":null,"Player_6_video":null,"Player_7":null,"Player_7_video":null,"Player_10":null,"Player_10_video":null,"Player_11":null,"Player_11_video":null,"Player_15":null,"Player_15_video":null,"Player_16":null,"Player_16_video":null,"Player_17":null,"Player_17_video":null,"Player_18":null,"Player_18_video":null,"Player_19":[26.0,26.0],"Player_19_video":[406.5,278.0],"Player_20":null,"Player_20_video":null,"Player_21":null,"Player_21_video":null,"Player_22":null,"Player_22_video":null,"Player_23":null,"Player_23_video":null,"Goalkeeper_14":null,"Goalkeeper_14_video":null,"Player_0":null,"Player_0_video":null,"Player_9":null,"Player_9_video":null,"Player_12":null,"Player_12_video":null,"Player_13":null,"Player_13_video":null,"Goalkeeper_5":null,"Goalkeeper_5_video":null,"Goalkeeper_8":null,"Goalkeeper_8_video":null,"Player_166":[45.0,6.0],"Player_166_video":[661.0,460.0],"Player_167":[52.0,13.0],"Player_167_video":[901.5,414.0],"Player_170":null,"Player_170_video":null,"Player_171":[35.0,18.0],"Player_171_video":[510.5,335.0],"Player_176":null,"Player_176_video":null,"Player_178":null,"Player_178_video":null,"Goalkeeper_172":null,"Goalkeeper_172_video":null,"Player_181":[51.0,2.0],"Player_181_video":[847.0,540.0],"Player_182":[53.0,26.0],"Player_182_video":[916.0,321.0],"Goalkeeper_196":[14.0,19.0],"Goalkeeper_196_video":[137.5,295.0],"Player_219":[57.0,41.0],"Player_219_video":[996.0,255.0],"Ball":[16.0,19.0],"Ball_video":[175.5,295.0]}]